Metadata-Version: 1.1
Name: PyTools5
Version: 0.0.3
Summary: A very basic way to do complex stuff in python.
Home-page: UNKNOWN
Author: Luke Dixon
Author-email: lukeodixon@gmail.com
License: MIT
Keywords: system
Platform: UNKNOWN
Classifier: Development Status :: 5 - Production/Stable
Classifier: Intended Audience :: Education
Classifier: Operating System :: Microsoft :: Windows :: Windows 10
Classifier: License :: OSI Approved :: MIT License
Classifier: Programming Language :: Python :: 3
